kicad_netlist_reader/__about__.py
kicad_netlist_reader/__init__.py
kicad_netlist_reader/kicad_netlist_reader.py
kicad_netlist_reader-7.0.1.dist-info/LICENSE
kicad_netlist_reader-7.0.1.dist-info/METADATA
kicad_netlist_reader-7.0.1.dist-info/WHEEL
kicad_netlist_reader-7.0.1.dist-info/top_level.txt
kicad_netlist_reader-7.0.1.dist-info/RECORD
