Metadata-Version: 2.1
Name: kicad_netlist_reader
Version: 7.0.1
Summary: KiCad python module for interpreting generic netlists which can be used to generate bills of materials.
Home-page: https://github.com/janelia-pypi/kicad_netlist_reader
Author: Jean-Pierre Charras
Author-email: jean-pierre.charras@wanadoo.fr
License: GPL-3.0
Platform: UNKNOWN
Classifier: Programming Language :: Python :: 3
License-File: LICENSE
